{"protocol":{"minReaderVersion":1,"minWriterVersion":2,"readerFeatures":null,"writerFeatures":null}}
{"metaData":{"id":"52a2d777-bc2e-433f-8818-3b7f4bb667bd","name":null,"description":null,"format":{"provider":"parquet","options":{}},"schemaString":"{\"type\":\"struct\",\"fields\":[{\"name\":\"SalesOrderID\",\"type\":\"integer\",\"nullable\":true,\"metadata\":{}},{\"name\":\"RevisionNumber\",\"type\":\"byte\",\"nullable\":true,\"metadata\":{}},{\"name\":\"OrderDate\",\"type\":\"timestamp\",\"nullable\":true,\"metadata\":{}},{\"name\":\"DueDate\",\"type\":\"timestamp\",\"nullable\":true,\"metadata\":{}},{\"name\":\"ShipDate\",\"type\":\"timestamp\",\"nullable\":true,\"metadata\":{}},{\"name\":\"Status\",\"type\":\"byte\",\"nullable\":true,\"metadata\":{}},{\"name\":\"OnlineOrderFlag\",\"type\":\"boolean\",\"nullable\":true,\"metadata\":{}},{\"name\":\"SalesOrderNumber\",\"type\":\"string\",\"nullable\":true,\"metadata\":{}},{\"name\":\"PurchaseOrderNumber\",\"type\":\"string\",\"nullable\":true,\"metadata\":{}},{\"name\":\"AccountNumber\",\"type\":\"string\",\"nullable\":true,\"metadata\":{}},{\"name\":\"CustomerID\",\"type\":\"integer\",\"nullable\":true,\"metadata\":{}},{\"name\":\"SalesPersonID\",\"type\":\"integer\",\"nullable\":true,\"metadata\":{}},{\"name\":\"TerritoryID\",\"type\":\"integer\",\"nullable\":true,\"metadata\":{}},{\"name\":\"BillToAddressID\",\"type\":\"integer\",\"nullable\":true,\"metadata\":{}},{\"name\":\"ShipToAddressID\",\"type\":\"integer\",\"nullable\":true,\"metadata\":{}},{\"name\":\"ShipMethodID\",\"type\":\"integer\",\"nullable\":true,\"metadata\":{}},{\"name\":\"CreditCardID\",\"type\":\"integer\",\"nullable\":true,\"metadata\":{}},{\"name\":\"CreditCardApprovalCode\",\"type\":\"string\",\"nullable\":true,\"metadata\":{}},{\"name\":\"CurrencyRateID\",\"type\":\"integer\",\"nullable\":true,\"metadata\":{}},{\"name\":\"SubTotal\",\"type\":\"double\",\"nullable\":true,\"metadata\":{}},{\"name\":\"TaxAmt\",\"type\":\"double\",\"nullable\":true,\"metadata\":{}},{\"name\":\"Freight\",\"type\":\"double\",\"nullable\":true,\"metadata\":{}},{\"name\":\"TotalDue\",\"type\":\"double\",\"nullable\":true,\"metadata\":{}},{\"name\":\"Comment\",\"type\":\"string\",\"nullable\":true,\"metadata\":{}},{\"name\":\"rowguid\",\"type\":\"string\",\"nullable\":true,\"metadata\":{}},{\"name\":\"ModifiedDate\",\"type\":\"timestamp\",\"nullable\":true,\"metadata\":{}}]}","partitionColumns":[],"createdTime":1702735022031,"configuration":{}}}
{"add":{"path":"0-5d87201a-8849-4c65-9374-aed132e8ad14-0.parquet","partitionValues":{},"size":3183988,"modificationTime":1702735022029,"dataChange":true,"stats":"{\"numRecords\": 31465, \"minValues\": {\"SalesOrderID\": 43659, \"RevisionNumber\": 10, \"OrderDate\": \"2019-05-31T00:00:00\", \"DueDate\": \"2019-06-12T00:00:00\", \"ShipDate\": \"2019-06-07T00:00:00\", \"Status\": 5, \"OnlineOrderFlag\": false, \"SalesOrderNumber\": \"SO43659\", \"PurchaseOrderNumber\": \"PO10005144378\", \"AccountNumber\": \"10-4020-000001\", \"CustomerID\": 11000, \"SalesPersonID\": 274, \"TerritoryID\": 1, \"BillToAddressID\": 405, \"ShipToAddressID\": 9, \"ShipMethodID\": 1, \"CreditCardID\": 1, \"CreditCardApprovalCode\": \"1016006Vi91301\", \"CurrencyRateID\": 2, \"SubTotal\": 1.374, \"TaxAmt\": 0.1099, \"Freight\": 0.0344, \"TotalDue\": 1.5183, \"rowguid\": \"0000de87-ab3f-4920-ac46-c404834241a0\", \"ModifiedDate\": \"2019-06-07T00:00:00\"}, \"maxValues\": {\"SalesOrderID\": 75123, \"RevisionNumber\": 11, \"OrderDate\": \"2022-06-30T00:00:00\", \"DueDate\": \"2022-07-12T00:00:00\", \"ShipDate\": \"2022-07-07T00:00:00\", \"Status\": 5, \"OnlineOrderFlag\": true, \"SalesOrderNumber\": \"SO75123\", \"PurchaseOrderNumber\": \"PO9976195169\", \"AccountNumber\": \"10-4030-029483\", \"CustomerID\": 30118, \"SalesPersonID\": 290, \"TerritoryID\": 10, \"BillToAddressID\": 29883, \"ShipToAddressID\": 29883, \"ShipMethodID\": 5, \"CreditCardID\": 19237, \"CreditCardApprovalCode\": \"98795Vi7192\", \"CurrencyRateID\": 12431, \"SubTotal\": 163930.3943, \"TaxAmt\": 17948.5186, \"Freight\": 5608.9121, \"TotalDue\": 187487.825, \"rowguid\": \"fffe293d-6cc6-445b-876d-955d4dbc5986\", \"ModifiedDate\": \"2022-07-07T00:00:00\"}, \"nullCount\": {\"SalesOrderID\": 0, \"RevisionNumber\": 0, \"OrderDate\": 0, \"DueDate\": 0, \"ShipDate\": 0, \"Status\": 0, \"OnlineOrderFlag\": 0, \"SalesOrderNumber\": 0, \"PurchaseOrderNumber\": 27659, \"AccountNumber\": 0, \"CustomerID\": 0, \"SalesPersonID\": 27659, \"TerritoryID\": 0, \"BillToAddressID\": 0, \"ShipToAddressID\": 0, \"ShipMethodID\": 0, \"CreditCardID\": 1131, \"CreditCardApprovalCode\": 1131, \"CurrencyRateID\": 17489, \"SubTotal\": 0, \"TaxAmt\": 0, \"Freight\": 0, \"TotalDue\": 0, \"Comment\": 31465, \"rowguid\": 0, \"ModifiedDate\": 0}}","tags":null,"deletionVector":null,"baseRowId":null,"defaultRowCommitVersion":null,"clusteringProvider":null}}
{"commitInfo":{"timestamp":1702735022032,"operation":"CREATE TABLE","operationParameters":{"location":"file:///Users/frank/Code/parquet-inspect/data/deltalake/sales_salesorderheader.delta","protocol":"{\"minReaderVersion\":1,\"minWriterVersion\":2,\"readerFeatures\":null,\"writerFeatures\":null}","mode":"ErrorIfExists","metadata":"{\"configuration\":{},\"created_time\":1702735022031,\"description\":null,\"format\":{\"options\":{},\"provider\":\"parquet\"},\"id\":\"52a2d777-bc2e-433f-8818-3b7f4bb667bd\",\"name\":null,\"partition_columns\":[],\"schema\":{\"fields\":[{\"metadata\":{},\"name\":\"SalesOrderID\",\"nullable\":true,\"type\":\"integer\"},{\"metadata\":{},\"name\":\"RevisionNumber\",\"nullable\":true,\"type\":\"byte\"},{\"metadata\":{},\"name\":\"OrderDate\",\"nullable\":true,\"type\":\"timestamp\"},{\"metadata\":{},\"name\":\"DueDate\",\"nullable\":true,\"type\":\"timestamp\"},{\"metadata\":{},\"name\":\"ShipDate\",\"nullable\":true,\"type\":\"timestamp\"},{\"metadata\":{},\"name\":\"Status\",\"nullable\":true,\"type\":\"byte\"},{\"metadata\":{},\"name\":\"OnlineOrderFlag\",\"nullable\":true,\"type\":\"boolean\"},{\"metadata\":{},\"name\":\"SalesOrderNumber\",\"nullable\":true,\"type\":\"string\"},{\"metadata\":{},\"name\":\"PurchaseOrderNumber\",\"nullable\":true,\"type\":\"string\"},{\"metadata\":{},\"name\":\"AccountNumber\",\"nullable\":true,\"type\":\"string\"},{\"metadata\":{},\"name\":\"CustomerID\",\"nullable\":true,\"type\":\"integer\"},{\"metadata\":{},\"name\":\"SalesPersonID\",\"nullable\":true,\"type\":\"integer\"},{\"metadata\":{},\"name\":\"TerritoryID\",\"nullable\":true,\"type\":\"integer\"},{\"metadata\":{},\"name\":\"BillToAddressID\",\"nullable\":true,\"type\":\"integer\"},{\"metadata\":{},\"name\":\"ShipToAddressID\",\"nullable\":true,\"type\":\"integer\"},{\"metadata\":{},\"name\":\"ShipMethodID\",\"nullable\":true,\"type\":\"integer\"},{\"metadata\":{},\"name\":\"CreditCardID\",\"nullable\":true,\"type\":\"integer\"},{\"metadata\":{},\"name\":\"CreditCardApprovalCode\",\"nullable\":true,\"type\":\"string\"},{\"metadata\":{},\"name\":\"CurrencyRateID\",\"nullable\":true,\"type\":\"integer\"},{\"metadata\":{},\"name\":\"SubTotal\",\"nullable\":true,\"type\":\"double\"},{\"metadata\":{},\"name\":\"TaxAmt\",\"nullable\":true,\"type\":\"double\"},{\"metadata\":{},\"name\":\"Freight\",\"nullable\":true,\"type\":\"double\"},{\"metadata\":{},\"name\":\"TotalDue\",\"nullable\":true,\"type\":\"double\"},{\"metadata\":{},\"name\":\"Comment\",\"nullable\":true,\"type\":\"string\"},{\"metadata\":{},\"name\":\"rowguid\",\"nullable\":true,\"type\":\"string\"},{\"metadata\":{},\"name\":\"ModifiedDate\",\"nullable\":true,\"type\":\"timestamp\"}],\"type\":\"struct\"}}"},"clientVersion":"delta-rs.0.17.0"}}